onsite/__init__.py
onsite/controller.py
onsite/env.py
onsite/observation.py
onsite/recorder.py
onsite/scenarioOrganizer.py
onsite/visualizer.py
onsite/opendrive2discretenet/__init__.py
onsite/opendrive2discretenet/converter.py
onsite/opendrive2discretenet/discrete_network.py
onsite/opendrive2discretenet/network.py
onsite/opendrive2discretenet/utils.py
onsite/opendrive2discretenet/opendriveparser/__init__.py
onsite/opendrive2discretenet/opendriveparser/parser.py
onsite/opendrive2discretenet/opendriveparser/elements/__init__.py
onsite/opendrive2discretenet/opendriveparser/elements/eulerspiral.py
onsite/opendrive2discretenet/opendriveparser/elements/geometry.py
onsite/opendrive2discretenet/opendriveparser/elements/junction.py
onsite/opendrive2discretenet/opendriveparser/elements/opendrive.py
onsite/opendrive2discretenet/opendriveparser/elements/road.py
onsite/opendrive2discretenet/opendriveparser/elements/roadElevationProfile.py
onsite/opendrive2discretenet/opendriveparser/elements/roadLanes.py
onsite/opendrive2discretenet/opendriveparser/elements/roadLateralProfile.py
onsite/opendrive2discretenet/opendriveparser/elements/roadLink.py
onsite/opendrive2discretenet/opendriveparser/elements/roadPlanView.py
onsite/opendrive2discretenet/opendriveparser/elements/road_record.py
onsite/opendrive2discretenet/opendriveparser/elements/roadtype.py
onsite/opendrive2discretenet/plane_elements/__init__.py
onsite/opendrive2discretenet/plane_elements/border.py
onsite/opendrive2discretenet/plane_elements/plane.py
onsite/opendrive2discretenet/plane_elements/plane_group.py
onsite-1.0.4.dist-info/LICENSE.txt
onsite-1.0.4.dist-info/METADATA
onsite-1.0.4.dist-info/WHEEL
onsite-1.0.4.dist-info/top_level.txt
onsite-1.0.4.dist-info/RECORD
