Metadata-Version: 2.1
Name: onsite
Version: 1.0.4
Summary: A tool package for Onsite
Home-page: https://gitee.com/huangyansmile/onsite-public
Author: Huang Yan
Author-email: huangyan520@tongji.edu.cn
Classifier: Programming Language :: Python :: 3
Classifier: License :: OSI Approved :: MIT License
Requires-Python: >=3.6
License-File: LICENSE.txt
Requires-Dist: numpy
Requires-Dist: shapely
Requires-Dist: pandas
Requires-Dist: matplotlib
Requires-Dist: scipy
Requires-Dist: lxml
